df_autoprofiler/__init__.py
df_autoprofiler/correlations.py
df_autoprofiler/dataset_summary.py
df_autoprofiler/missing.py
df_autoprofiler/outliers.py
df_autoprofiler/profiler.py
df_autoprofiler/report.py
df_autoprofiler/suggestions.py
df_autoprofiler/summary.py
df_autoprofiler/utils.py
df_autoprofiler/visuals/__init__.py
df_autoprofiler/visuals/plots.py
df_autoprofiler-0.1.1.dist-info/licenses/LICENSE
df_autoprofiler-0.1.1.dist-info/METADATA
df_autoprofiler-0.1.1.dist-info/WHEEL
df_autoprofiler-0.1.1.dist-info/top_level.txt
df_autoprofiler-0.1.1.dist-info/RECORD
