Metadata-Version: 2.4
Name: df-autoprofiler
Version: 0.1.1
Summary: Automated data profiling and exploratory analysis for tabular datasets.
Author: Cameron Scolari
License-Expression: MIT
Project-URL: Homepage, https://github.com/cameronscolari/autoprofiler
Project-URL: Repository, https://github.com/cameronscolari/autoprofiler
Keywords: data-analysis,data-science,profiling,EDA,pandas,matplotlib,seaborn
Classifier: Programming Language :: Python :: 3
Classifier: Operating System :: OS Independent
Classifier: Intended Audience :: Science/Research
Classifier: Intended Audience :: Developers
Classifier: Topic :: Scientific/Engineering :: Information Analysis
Classifier: Topic :: Software Development :: Libraries
Requires-Python: >=3.9
License-File: LICENSE
Requires-Dist: pandas
Requires-Dist: matplotlib
Requires-Dist: scipy
Requires-Dist: seaborn
Dynamic: license-file
